README.md
setup.cfg
setup.py
cloudmersive_video_api_client/__init__.py
cloudmersive_video_api_client/api_client.py
cloudmersive_video_api_client/configuration.py
cloudmersive_video_api_client/rest.py
cloudmersive_video_api_client.egg-info/PKG-INFO
cloudmersive_video_api_client.egg-info/SOURCES.txt
cloudmersive_video_api_client.egg-info/dependency_links.txt
cloudmersive_video_api_client.egg-info/requires.txt
cloudmersive_video_api_client.egg-info/top_level.txt
cloudmersive_video_api_client/api/__init__.py
cloudmersive_video_api_client/api/audio_api.py
cloudmersive_video_api_client/api/video_api.py
cloudmersive_video_api_client/models/__init__.py
cloudmersive_video_api_client/models/media_information.py
cloudmersive_video_api_client/models/nsfw_result.py
cloudmersive_video_api_client/models/nsfw_scanned_frame.py
cloudmersive_video_api_client/models/split_video_result.py
cloudmersive_video_api_client/models/still_frame.py
cloudmersive_video_api_client/models/still_frames_result.py
cloudmersive_video_api_client/models/video_file.py
test/__init__.py
test/test_audio_api.py
test/test_media_information.py
test/test_nsfw_result.py
test/test_nsfw_scanned_frame.py
test/test_split_video_result.py
test/test_still_frame.py
test/test_still_frames_result.py
test/test_video_api.py
test/test_video_file.py