Metadata-Version: 2.1
Name: cloudmersive-video-api-client
Version: 3.0.3
Summary: videoapi
Home-page: https://cloudmersive.com/video-and-media-services-api
Author-email: 
License: UNKNOWN
Keywords: Swagger,videoapi
Platform: UNKNOWN
